config
watcher
