Metadata-Version: 1.1
Name: django-collecstatic-daemon
Version: 0.3
Summary: A simple daemon to watch and collectstatic files for django projects
Home-page: UNKNOWN
Author: John Furr
Author-email: john.furr@gmail.com
License: GNU General Public License v3.0
Platform: UNKNOWN
Classifier: Environment :: Web Environment
Classifier: Framework :: Django
Classifier: Framework :: Django :: 2.2
Classifier: Intended Audience :: Developers
Classifier: License :: OSI Approved :: BSD License
Classifier: Operating System :: OS Independent
Classifier: Programming Language :: Python
Classifier: Programming Language :: Python :: 3.5
Classifier: Programming Language :: Python :: 3.6
Classifier: Topic :: Internet :: WWW/HTTP
Classifier: Topic :: Internet :: WWW/HTTP :: Dynamic Content
